pytorchfi/__init__.py
pytorchfi/core.py
pytorchfi/neuron_error_models.py
pytorchfi/util.py
pytorchfi/weight_error_models.py
test/__init__.py
test/test_example_client.py
test/test_get_funcs.py
test/test_init.py
test/test_layers.py
test/test_neuron_error_models.py
test/test_neuron_fi.py
test/test_weight_error_models.py
test/test_weight_fi.py
test/util_test.py
pytorchfi-0.6.0.dist-info/LICENSE
pytorchfi-0.6.0.dist-info/METADATA
pytorchfi-0.6.0.dist-info/WHEEL
pytorchfi-0.6.0.dist-info/top_level.txt
pytorchfi-0.6.0.dist-info/RECORD
