Metadata-Version: 2.1
Name: pytorchfi
Version: 0.6.0
Summary: UNKNOWN
Home-page: https://github.com/pytorchfi/pytorchfi
Author: UIUC RSim
License: UNKNOWN
Project-URL: Source Code, https://github.com/pytorchfi/pytorchfi
Project-URL: Documentation, https://www.pytorchfi.dev/
Platform: UNKNOWN
Classifier: Programming Language :: Python :: 3
Classifier: Operating System :: OS Independent
